ltvpy/__init__.py
ltvpy/decode.py
ltvpy/encode.py
ltvpy/protocol.py
ltvpy-1.0.0.dist-info/METADATA
ltvpy-1.0.0.dist-info/WHEEL
ltvpy-1.0.0.dist-info/licenses/LICENSE
ltvpy-1.0.0.dist-info/RECORD
