Metadata-Version: 2.1
Name: ltvpy
Version: 1.0.0
Summary: Compact implementation of a LiteVector serializer in pure Python
Project-URL: Homepage, https://litevectors.org/
Project-URL: Source, https://github.com/LitePipe/ltvpy
Project-URL: Bug Tracker, https://github.com/LitePipe/ltvpy/issues
Author-email: Thad Thompson <thad@litepipe.com>
License: MIT License
License-File: LICENSE
Classifier: Intended Audience :: Developers
Classifier: License :: OSI Approved :: MIT License
Classifier: Operating System :: OS Independent
Classifier: Programming Language :: Python :: 3
Requires-Python: >=3.7
Requires-Dist: numpy>=1.15
